aecroscopy/__init__.py
aecroscopy/__version__.py
aecroscopy/acquisition/AEBE.py
aecroscopy/acquisition/AECypher.py
aecroscopy/acquisition/AEICON.py
aecroscopy/acquisition/AEJupiter.py
aecroscopy/acquisition/AEMFP.py
aecroscopy/acquisition/AENanoSurf.py
aecroscopy/acquisition/__init__.py
aecroscopy/acquisition/aemd.py
aecroscopy/acquisition/aemd_bsky.py
aecroscopy/base/__init__.py
aecroscopy/base/sid_utilities.py
aecroscopy/communication/__init__.py
aecroscopy/communication/client.py
aecroscopy/communication/client_test.py
aecroscopy/communication/server.py
aecroscopy/communication/server_test.py
aecroscopy/communication/server_test_final.py
aecroscopy/dashboard/__init__.py
aecroscopy/dashboard/dashboard_app.py
aecroscopy/processing/__init__.py
aecroscopy/processing/linear_fits.py
aecroscopy/processing/pbase.py
aecroscopy/processing/sho_fitting.py
aecroscopy/processing/tools.py
aecroscopy/utilities/__init__.py
aecroscopy/utilities/control_cluster.py
aecroscopy/utilities/fit.py
aecroscopy/utilities/utils.py
aecroscopy/utilities/waveforms.py
aecroscopy-0.0.2.dist-info/METADATA
aecroscopy-0.0.2.dist-info/WHEEL
aecroscopy-0.0.2.dist-info/top_level.txt
aecroscopy-0.0.2.dist-info/RECORD
