Metadata-Version: 2.4
Name: aecroscopy
Version: 0.0.2
Summary: Acquisition software for microscopy developed at CNMS ORNL
Home-page: https://code.ornl.gov/rvv/aecroscopy
Author: Rama Vasudevan, Yongtao Liu, Mani Valleti
License: MIT
Dynamic: author
Dynamic: description
Dynamic: description-content-type
Dynamic: home-page
Dynamic: license
Dynamic: summary
